new_nlp_smvec/Exp2.py
new_nlp_smvec/__init__.py
new_nlp_smvec/chatbot.py
new_nlp_smvec/exp10.py
new_nlp_smvec/exp3.py
new_nlp_smvec/exp4.py
new_nlp_smvec/exp5.py
new_nlp_smvec/exp6.py
new_nlp_smvec/exp7.py
new_nlp_smvec/exp8.py
new_nlp_smvec/exp9.py
new_nlp_smvec-0.1.dist-info/METADATA
new_nlp_smvec-0.1.dist-info/WHEEL
new_nlp_smvec-0.1.dist-info/top_level.txt
new_nlp_smvec-0.1.dist-info/RECORD
